{
  "generatedAt": "2026-07-01T04:02:32.147Z",
  "updateStatus": "Облачный импорт выполнен частично; недоступны: HeadHunter, Rabota1000, ЦентрРабота",
  "fallback": false,
  "sourcesChecked": 39,
  "sourcesConnected": 7,
  "sourceRuns": [
    {
      "name": "HeadHunter",
      "mode": "auto",
      "status": "blocked",
      "found": 0,
      "error": "HH /vacancies HTTP 403",
      "retained": 25
    },
    {
      "name": "Работа России",
      "mode": "auto",
      "status": "ok",
      "found": 66
    },
    {
      "name": "FarPost",
      "mode": "auto",
      "status": "ok",
      "found": 185
    },
    {
      "name": "Публичный Telegram",
      "mode": "auto",
      "status": "ok",
      "found": 21
    },
    {
      "name": "ГдеРабота",
      "mode": "auto",
      "status": "ok",
      "found": 146
    },
    {
      "name": "Спасский завод ЖБИ",
      "mode": "auto",
      "status": "ok",
      "found": 3
    },
    {
      "name": "Rabota1000",
      "mode": "auto",
      "status": "blocked",
      "found": 0,
      "error": "robots.txt запрещает путь /spassk-dalni"
    },
    {
      "name": "ЦентрРабота",
      "mode": "auto",
      "status": "blocked",
      "found": 0,
      "error": "robots.txt недоступен — импорт отменён безопасно: centrrabota.ru HTTP 403"
    },
    {
      "name": "Проверенные публичные страницы работодателей",
      "mode": "curated",
      "status": "ok",
      "found": 11,
      "expired": 0,
      "note": "Ручной FarPost-срез отключён, так как живой импорт успешен"
    },
    {
      "name": "HeadHunter — последний проверенный срез",
      "mode": "fallback",
      "status": "ok",
      "found": 28
    }
  ],
  "raw": 485,
  "accepted": 363,
  "remote": 0,
  "rejected": {
    "otherCity": 21,
    "imprecise": 30,
    "remote": 0,
    "duplicate": 71
  },
  "stats": {
    "active": 363,
    "noExperience": 100,
    "noHigherEducation": 333,
    "withSalary": 348,
    "goodFit": 160,
    "newVacancies": 7,
    "changedVacancies": 16,
    "strongOpportunities": 1
  },
  "changes": {
    "new": 7,
    "changed": 16,
    "closed": 5
  },
  "policy": "Основной список: только явный Спасск-Дальний; общерегиональные, другие города, вахта и переезд исключены."
}