{
  "generatedAt": "2026-06-30T08:39:06.414Z",
  "updateStatus": "Облачный импорт выполнен частично; недоступны: HeadHunter, Rabota1000, ЦентрРабота",
  "fallback": false,
  "sourcesChecked": 39,
  "sourcesConnected": 7,
  "sourceRuns": [
    {
      "name": "HeadHunter",
      "mode": "auto",
      "status": "blocked",
      "found": 0,
      "error": "HH /vacancies HTTP 403",
      "retained": 26
    },
    {
      "name": "Работа России",
      "mode": "auto",
      "status": "ok",
      "found": 65
    },
    {
      "name": "FarPost",
      "mode": "auto",
      "status": "ok",
      "found": 192
    },
    {
      "name": "Публичный Telegram",
      "mode": "auto",
      "status": "ok",
      "found": 21
    },
    {
      "name": "ГдеРабота",
      "mode": "auto",
      "status": "ok",
      "found": 131
    },
    {
      "name": "Спасский завод ЖБИ",
      "mode": "auto",
      "status": "ok",
      "found": 3
    },
    {
      "name": "Rabota1000",
      "mode": "auto",
      "status": "blocked",
      "found": 0,
      "error": "robots.txt запрещает путь /spassk-dalni"
    },
    {
      "name": "ЦентрРабота",
      "mode": "auto",
      "status": "blocked",
      "found": 0,
      "error": "robots.txt недоступен — импорт отменён безопасно: centrrabota.ru HTTP 403"
    },
    {
      "name": "Проверенные публичные страницы работодателей",
      "mode": "curated",
      "status": "ok",
      "found": 11,
      "expired": 0,
      "note": "Ручной FarPost-срез отключён, так как живой импорт успешен"
    },
    {
      "name": "HeadHunter — последний проверенный срез",
      "mode": "fallback",
      "status": "ok",
      "found": 28
    }
  ],
  "raw": 477,
  "accepted": 350,
  "remote": 1,
  "rejected": {
    "otherCity": 25,
    "imprecise": 30,
    "remote": 1,
    "duplicate": 71
  },
  "stats": {
    "active": 350,
    "noExperience": 94,
    "noHigherEducation": 322,
    "withSalary": 338,
    "goodFit": 160,
    "newVacancies": 15,
    "changedVacancies": 73,
    "strongOpportunities": 3
  },
  "changes": {
    "new": 15,
    "changed": 73,
    "closed": 5
  },
  "policy": "Основной список: только явный Спасск-Дальний; общерегиональные, другие города, вахта и переезд исключены."
}